CHANGES.txt
LICENSE.txt
MANIFEST.in
README.md
setup.py
iugu/__init__.py
iugu/action.py
iugu/customer.py
iugu/exception.py
iugu/invoice.py
iugu/iuguapi.py
iugu/marketplace.py
iugu/plan.py
iugu/subscription.py
iugu/token.py
iugu/transfer.py
iugu/version.py
iuguCTS.egg-info/PKG-INFO
iuguCTS.egg-info/SOURCES.txt
iuguCTS.egg-info/dependency_links.txt
iuguCTS.egg-info/top_level.txt