Metadata-Version: 2.1
Name: iuguCTS
Version: 0.0.1
Summary: SDK iugu
Home-page: https://pypi.org/project/iugu/
Author: SDK_PS
Author-email: marcus.silva@monetizze.com.br
License: MIT License
Keywords: iugu
License-File: LICENSE.txt
